stanfordkarel/__init__.py
stanfordkarel/didyoumean.py
stanfordkarel/icon.png
stanfordkarel/karel_application.py
stanfordkarel/karel_ascii.py
stanfordkarel/karel_canvas.py
stanfordkarel/karel_program.py
stanfordkarel/karel_world.py
stanfordkarel/py.typed
stanfordkarel/stanfordkarel.py
stanfordkarel/style_checker.py
stanfordkarel/world_editor.py
stanfordkarel/worlds/1x1.w
stanfordkarel/worlds/1x8.w
stanfordkarel/worlds/2x2.w
stanfordkarel/worlds/2x8.w
stanfordkarel/worlds/3x5.w
stanfordkarel/worlds/40x40.w
stanfordkarel/worlds/5x3.w
stanfordkarel/worlds/5x5.w
stanfordkarel/worlds/6x5.w
stanfordkarel/worlds/7x7.w
stanfordkarel/worlds/8x1.w
stanfordkarel/worlds/8x2.w
stanfordkarel/worlds/8x8.w
stanfordkarel/worlds/checkerboard_karel.w
stanfordkarel/worlds/checkerboard_karel_end.w
stanfordkarel/worlds/collect_newspaper_karel.w
stanfordkarel/worlds/collect_newspaper_karel_end.w
stanfordkarel/worlds/color_karel.w
stanfordkarel/worlds/default_world.w
stanfordkarel/worlds/extension_karel.w
stanfordkarel/worlds/garden_karel.w
stanfordkarel/worlds/gg.w
stanfordkarel/worlds/hospital_karel.w
stanfordkarel/worlds/midpoint_finding_karel.w
stanfordkarel/worlds/midpoint_karel.w
stanfordkarel/worlds/midpoint_karel_end.w
stanfordkarel/worlds/sample_quad1.w
stanfordkarel/worlds/sample_quad2.w
stanfordkarel/worlds/square_karel.w
stanfordkarel/worlds/stone_mason_karel.w
stanfordkarel/worlds/stone_mason_karel_end.w
stanfordkarel/worlds/triple1.w
stanfordkarel/worlds/triple2.w
stanfordkarel/worlds/triple3.w
stanfordkarel/worlds/triple_karel.w
stanfordkarel/worlds/triple_karel_end.w
stanfordkarel-0.2.7.dist-info/LICENSE
stanfordkarel-0.2.7.dist-info/METADATA
stanfordkarel-0.2.7.dist-info/WHEEL
stanfordkarel-0.2.7.dist-info/top_level.txt
stanfordkarel-0.2.7.dist-info/RECORD
