Metadata-Version: 2.1
Name: stanfordkarel
Version: 0.2.7
Summary: Official Stanford Karel library used in CS 106A
Home-page: https://github.com/tyleryep/stanford-karel
Author: Tyler Yep
Author-email: tyep@cs.stanford.edu
License: MIT
Classifier: License :: OSI Approved :: MIT License
Classifier: Operating System :: OS Independent
Classifier: Programming Language :: Python :: 3
Classifier: Programming Language :: Python :: 3 :: Only
Classifier: Programming Language :: Python :: 3.7
Classifier: Programming Language :: Python :: 3.8
Classifier: Programming Language :: Python :: 3.9
Classifier: Programming Language :: Python :: 3.10
Classifier: Programming Language :: Python :: 3.11
Requires-Python: >=3.7
License-File: LICENSE
